Metadata-Version: 2.1
Name: fbc_for_python
Version: 1.1
Summary: FBC指纹浏览器 RPA SDK for python
Home-page: https://github.com/srankXY/fbc-for-python
Author: srank
Author-email: 625593240@qq.com
License: GNU General Public License v3.0
Requires-Dist: requests
